papi_iot/__init__.py
papi_iot/cli.py
papi_iot/papi_camera_video.py
papi_iot/papi_exceptions.py
papi_iot/papi_face_recognition.py
papi_iot/papi_iot.py
papi_iot/papi_storage_manager.py
papi_iot/papi_storage_offline.py
papi_iot/papi_storage_online.py
papi_iot-3.7.8.dist-info/AUTHORS.rst
papi_iot-3.7.8.dist-info/LICENSE
papi_iot-3.7.8.dist-info/METADATA
papi_iot-3.7.8.dist-info/WHEEL
papi_iot-3.7.8.dist-info/entry_points.txt
papi_iot-3.7.8.dist-info/top_level.txt
papi_iot-3.7.8.dist-info/RECORD
