Metadata-Version: 2.1
Name: papi-iot
Version: 3.7.8
Summary: An API for IOT application with emphasis on some module
Home-page: https://github.com/Stelele/papi_iot
Author: Gift Mugweni
Author-email: giftmugweni@gmail.com
License: MIT license
Keywords: papi_iot
Platform: UNKNOWN
Classifier: Development Status :: 2 - Pre-Alpha
Classifier: Intended Audience :: Developers
Classifier: License :: OSI Approved :: MIT License
Classifier: Natural Language :: English
Classifier: Programming Language :: Python :: 3
Classifier: Programming Language :: Python :: 3.6
Classifier: Programming Language :: Python :: 3.7
Classifier: Programming Language :: Python :: 3.8
Requires-Python: >=3.5
